clapback/__init__.py
clapback/clapback.py
clapback-0.0.1.dist-info/METADATA
clapback-0.0.1.dist-info/RECORD
clapback-0.0.1.dist-info/WHEEL
clapback-0.0.1.dist-info/top_level.txt
